primalscheme/__init__.py
primalscheme/__main__.py
primalscheme/align.py
primalscheme/cli.py
primalscheme/config.py
primalscheme/multiplex.py
primalscheme/primer.py
primalscheme/region.py
primalscheme/reporting.py
primalscheme-1.4.1.dist-info/entry_points.txt
primalscheme-1.4.1.dist-info/LICENSE
primalscheme-1.4.1.dist-info/WHEEL
primalscheme-1.4.1.dist-info/METADATA
primalscheme-1.4.1.dist-info/RECORD
