Metadata-Version: 2.1
Name: primalscheme
Version: 1.4.1
Summary: primalscheme is a tool for designing primer panels for multiplex PCR
Home-page: https://github.com/aresti/primalscheme
Author: Josh Quick
Author-email: j.quick@bham.ac.uk
Maintainer: Andrew Smith
Maintainer-email: andysmith.d@gmail.com
Requires-Python: >=3.7,<4
Classifier: Programming Language :: Python :: 3.7
Classifier: License :: OSI Approved :: GNU General Public License v3 (GPLv3)
Classifier: Operating System :: OS Independent
Requires-Dist: biopython>=1,<2
Requires-Dist: click==8.1.3
Requires-Dist: parasail==1.2
Requires-Dist: primer3-py>=0,<1
Requires-Dist: progress==1.5
Requires-Dist: reportlab>=3,<4
Requires-Dist: pre-commit ; extra == "dev"
Requires-Dist: pytest >=2.7.3 ; extra == "test"
Requires-Dist: pytest-cov ; extra == "test"
Provides-Extra: dev
Provides-Extra: test
